dhananjayashoktrial-0.1.0.dist-info/licenses/LICENSE
poke_env/__init__.py
poke_env/testing.py
poke_env/emulators/__init__.py
poke_env/emulators/emulator.py
poke_env/emulators/pokemon_red_emulator.py
poke_env/utils/__init__.py
poke_env/utils/fundamental.py
poke_env/utils/log_handling.py
poke_env/utils/parameter_handling.py
dhananjayashoktrial-0.1.0.dist-info/METADATA
dhananjayashoktrial-0.1.0.dist-info/WHEEL
dhananjayashoktrial-0.1.0.dist-info/top_level.txt
dhananjayashoktrial-0.1.0.dist-info/RECORD
